[
    {
        "repo_name": "wazuh/wazuh",
        "Target PR": "https://github.com/wazuh/wazuh/pull/8092",
        "Closest PR": "https://github.com/wazuh/wazuh/pull/12946",
        "Title": "Fix to process unknown registry value types in FIM sync",
        "Created At": "2022-03-31T12:49:25Z",
        "Target Commit SHA": null,
        "target_inducing_commit_hash_pyszz": "-",
        "Closest Commit SHA": "480be37e9a53673eac81b373df31e9612dc1fe1d",
        "closest_inducing_commit_hash_pyszz": "-",
        "target_inducing_commit_hash_pd": [],
        "target_matched": [],
        "closest_inducing_commit_hash_pd": [],
        "closest_matched": []
    }
]