[
    {
        "repo_name": "xm-online/xm-uaa",
        "Target PR": "https://github.com/xm-online/xm-uaa/pull/61",
        "Closest PR": "https://github.com/xm-online/xm-uaa/pull/127",
        "Title": "fix envs",
        "Created At": "2020-06-01T11:23:51Z",
        "Target Commit SHA": "32a27e5876ef871938679f3a958f1c777e20d838",
        "target_inducing_commit_hash_pyszz": "-",
        "Closest Commit SHA": "a8623afcdea7b105456ba1d1fa2f54584256e224",
        "closest_inducing_commit_hash_pyszz": "-",
        "target_inducing_commit_hash_pd": [],
        "target_matched": [],
        "closest_inducing_commit_hash_pd": [],
        "closest_matched": []
    }
]