[
    {
        "repo_name": "apache/pinot",
        "id": "226",
        "repo_id": "187",
        "terms_vulnerability": "secur",
        "url": "https://github.com/apache/pinot/pull/6774",
        "fix_commit_hash": null
    },
    {
        "repo_name": "apache/pinot",
        "id": "228",
        "repo_id": "187",
        "terms_vulnerability": "vulner",
        "url": "https://github.com/apache/pinot/pull/5941",
        "fix_commit_hash": "a31c06a9f77314234190cdd77d4657bc373d4e89"
    },
    {
        "repo_name": "apache/pinot",
        "id": "229",
        "repo_id": "187",
        "terms_vulnerability": "vulner",
        "url": "https://github.com/apache/pinot/pull/5896",
        "fix_commit_hash": "e9ad1e017bf06ac579014357462c86861a31cf7d"
    },
    {
        "repo_name": "apache/pinot",
        "id": "230",
        "repo_id": "187",
        "terms_vulnerability": "vulner",
        "url": "https://github.com/apache/pinot/pull/5888",
        "fix_commit_hash": "41dc432e775aeeb841f57bd25525832950698739"
    }
]