[
    {
        "repo_name": "atom/atom",
        "id": "2433",
        "repo_id": "94399",
        "terms_vulnerability": "secur",
        "url": "https://github.com/atom/atom/pull/17770"
    },
    {
        "repo_name": "atom/atom",
        "id": "2434",
        "repo_id": "94399",
        "terms_vulnerability": "secur",
        "url": "https://github.com/atom/atom/pull/16444"
    },
    {
        "repo_name": "atom/atom",
        "id": "2435",
        "repo_id": "94399",
        "terms_vulnerability": "secur",
        "url": "https://github.com/atom/atom/pull/16221"
    },
    {
        "repo_name": "atom/atom",
        "id": "2436",
        "repo_id": "94399",
        "terms_vulnerability": "secur",
        "url": "https://github.com/atom/atom/pull/16197"
    },
    {
        "repo_name": "atom/atom",
        "id": "2437",
        "repo_id": "94399",
        "terms_vulnerability": "secur",
        "url": "https://github.com/atom/atom/pull/16190"
    },
    {
        "repo_name": "atom/atom",
        "id": "2438",
        "repo_id": "94399",
        "terms_vulnerability": "secur",
        "url": "https://github.com/atom/atom/pull/16180"
    },
    {
        "repo_name": "atom/atom",
        "id": "2440",
        "repo_id": "94399",
        "terms_vulnerability": "secur",
        "url": "https://github.com/atom/atom/pull/14761"
    },
    {
        "repo_name": "atom/atom",
        "id": "2441",
        "repo_id": "94399",
        "terms_vulnerability": "secur",
        "url": "https://github.com/atom/atom/pull/12585"
    },
    {
        "repo_name": "atom/atom",
        "id": "2442",
        "repo_id": "94399",
        "terms_vulnerability": "secur",
        "url": "https://github.com/atom/atom/pull/12565"
    },
    {
        "repo_name": "atom/atom",
        "id": "2447",
        "repo_id": "94399",
        "terms_vulnerability": "secur",
        "url": "https://github.com/atom/atom/pull/10228"
    },
    {
        "repo_name": "atom/atom",
        "id": "2449",
        "repo_id": "94399",
        "terms_vulnerability": "secur",
        "url": "https://github.com/atom/atom/pull/8697"
    },
    {
        "repo_name": "atom/atom",
        "id": "2451",
        "repo_id": "94399",
        "terms_vulnerability": "secur",
        "url": "https://github.com/atom/atom/pull/4006"
    },
    {
        "repo_name": "atom/atom",
        "id": "2458",
        "repo_id": "94399",
        "terms_vulnerability": "secur",
        "url": "https://github.com/atom/atom/pull/1702"
    },
    {
        "repo_name": "atom/atom",
        "id": "2461",
        "repo_id": "94399",
        "terms_vulnerability": "secur",
        "url": "https://github.com/atom/atom/pull/1035"
    },
    {
        "repo_name": "atom/atom",
        "id": "2462",
        "repo_id": "94399",
        "terms_vulnerability": "secur",
        "url": "https://github.com/atom/atom/pull/869"
    }
]