[
    {
        "repo_name": "mock-server/mockserver",
        "Target PR": "https://github.com/mock-server/mockserver/pull/555",
        "Closest PR": "https://github.com/mock-server/mockserver/pull/673",
        "Closest Commit SHA": "98eff57639cae9ac820389b16e2f92645acb8552",
        "Title": "Adding global thread-safety to javascript process for local variables defined without keyword var",
        "Created At": "2019-09-29T17:51:17Z",
        "fix_commit_hash": "e2b0be7257cf88e5d624fbafcd2a3a844df2ffd3"
    }
]